geminus/__init__.py
tests/__init__.py
geminus-0.0.1.dist-info/LICENSE
geminus-0.0.1.dist-info/METADATA
geminus-0.0.1.dist-info/WHEEL
geminus-0.0.1.dist-info/top_level.txt
geminus-0.0.1.dist-info/RECORD
