Metadata-Version: 2.1
Name: geminus
Version: 0.0.1
Summary: Geminus platform client
Home-page: https://github.com/Geminus-AI/geminus
Author: Geminus.ai, Inc
Author-email: info@geminus.ai
License: UNKNOWN
Platform: UNKNOWN
Classifier: Programming Language :: Python :: 3 :: Only
Classifier: License :: OSI Approved :: BSD License
Classifier: Operating System :: OS Independent
Classifier: Development Status :: 1 - Planning
Classifier: Natural Language :: English
Classifier: Topic :: Scientific/Engineering
Classifier: Topic :: Software Development :: Libraries
Requires-Dist: numpy (>=1.18.0)
Requires-Dist: pandas (>=1.0.0)
Requires-Dist: xlrd (>=1.2.0)
Requires-Dist: scipy (>=1.1.0)
